petrel/__init__.py
petrel/version.py
petrel/dataset/__init__.py
petrel/dataset/petrel.py
petrel/dataset/train_data.py
petrel/dataset/val_data.py
petrel/model/__init__.py
petrel/model/bench.py
petrel/model/counter.py
petrel/model/edet.py
petrel/model/loss.py
petrel/model/optimizer.py
petrel/model/scheduler.py
petrel/model/trainer.py
petrel/predict/__init__.py
petrel/predict/eval.py
petrel/predict/predict.py
tests/__init__.py
tests/dataset/__init__.py
tests/model/__init__.py
tests/model/test_counter.py
tests/model/test_edet.py
tests/model/test_loss.py
tests/model/test_optimizer.py
tests/model/test_scheduler.py
petrel_det-0.2.2.dist-info/LICENSE
petrel_det-0.2.2.dist-info/METADATA
petrel_det-0.2.2.dist-info/WHEEL
petrel_det-0.2.2.dist-info/top_level.txt
petrel_det-0.2.2.dist-info/RECORD
