Metadata-Version: 2.1
Name: petrel-det
Version: 0.2.2
Summary: Code to streamline Pytorch EfficientDet applications
Home-page: https://github.com/DanielMorton/Petrel
Author: Daniel Morton
License: UNKNOWN
Platform: UNKNOWN
Classifier: Development Status :: 3 - Alpha
Classifier: Intended Audience :: Education
Classifier: Intended Audience :: Science/Research
Classifier: License :: OSI Approved :: Apache Software License
Classifier: Programming Language :: Python :: 3.7
Classifier: Programming Language :: Python :: 3.8
Classifier: Topic :: Scientific/Engineering
Classifier: Topic :: Scientific/Engineering :: Artificial Intelligence
Classifier: Topic :: Software Development
Classifier: Topic :: Software Development :: Libraries
Classifier: Topic :: Software Development :: Libraries :: Python Modules
Requires-Python: >=3.7
License-File: LICENSE
Requires-Dist: albumentations (>=1.0.3)
Requires-Dist: effdet (>=0.2.4)
Requires-Dist: opencv-python (>=4.5.2.54)
Requires-Dist: pandas (>=1.1.5)
Requires-Dist: torch (>=1.9)
